{
  "title": "Fix analog components to match corrected FALSTAD references",
  "stories": [
    {
      "id": "US-001",
      "title": "Pin-only fixes for passives, sources, and semiconductors",
      "passes": false,
      "acceptanceCriteria": [
        "Zero pin position mismatches for all 12 components",
        "Dice >= 0.99 maintained for all",
        "No new detached pin failures"
      ]
    },
    {
      "id": "US-002",
      "title": "Draw + pin count fixes: DcVoltageSource, OpAmp, VariableRail, SCR, Triac, Triode",
      "passes": false,
      "acceptanceCriteria": [
        "DcVoltageSource Dice >= 0.99",
        "OpAmp pin count delta = 0",
        "VariableRail pin count delta = 0",
        "SCR/Triac no detached pins",
        "Triode Dice >= 0.99 and no detached pins"
      ]
    },
    {
      "id": "US-003",
      "title": "Final: zero audit failures",
      "passes": false,
      "acceptanceCriteria": [
        "All 98 tests pass with 0 failures"
      ]
    }
  ]
}
